{
  "name": "Email Verification Workflow - Fixed",
  "nodes": [
    {
      "parameters": {
        "httpMethod": "POST",
        "path": "send-verification-email",
        "responseMode": "responseNode",
        "options": {}
      },
      "id": "webhook-node",
      "name": "Webhook",
      "type": "n8n-nodes-base.webhook",
      "typeVersion": 1.1,
      "position": [300, 300],
      "webhookId": "verification-email-webhook"
    },
    {
      "parameters": {
        "conditions": {
          "options": {
            "caseSensitive": true,
            "leftValue": "",
            "typeValidation": "strict"
          },
          "conditions": [
            {
              "id": "condition-1",
              "leftValue": "={{ $json.type }}",
              "rightValue": "verification",
              "operator": {
                "type": "string",
                "operation": "equals"
              }
            }
          ],
          "combinator": "and"
        },
        "options": {}
      },
      "id": "if-node",
      "name": "Check Email Type",
      "type": "n8n-nodes-base.if",
      "typeVersion": 2,
      "position": [500, 300]
    },
    {
      "parameters": {
        "authentication": "oAuth2",
        "sendTo": "={{ $json.to }}",
        "subject": "Verify Your Email - Sanrico Mercantile",
        "emailType": "html",
        "message": "<!DOCTYPE html>\n<html>\n<head>\n    <meta charset=\"UTF-8\">\n    <title>Email Verification - Sanrico Mercantile</title>\n    <style>\n        body {\n            font-family: 'Segoe UI', Tahoma, Geneva, Verdana, sans-serif;\n            background: linear-gradient(135deg, #667eea 0%, #764ba2 100%);\n            margin: 0;\n            padding: 20px;\n            min-height: 100vh;\n        }\n        .container {\n            max-width: 600px;\n            margin: 0 auto;\n            background: white;\n            border-radius: 20px;\n            padding: 40px;\n            box-shadow: 0 20px 60px rgba(0,0,0,0.1);\n            text-align: center;\n        }\n        .logo-container {\n            margin-bottom: 20px;\n        }\n        .logo {\n            max-width: 200px;\n            height: auto;\n            margin-bottom: 10px;\n        }\n        .company-name {\n            color: #3498db;\n            font-size: 32px;\n            font-weight: bold;\n            margin-bottom: 10px;\n        }\n        .subtitle {\n            color: #666;\n            font-size: 16px;\n            margin-bottom: 30px;\n        }\n        .greeting {\n            font-size: 20px;\n            color: #2c3e50;\n            margin-bottom: 20px;\n        }\n        .verification-code {\n            background: linear-gradient(45deg, #3498db, #2980b9);\n            color: white;\n            font-size: 36px;\n            font-weight: bold;\n            padding: 20px 40px;\n            border-radius: 15px;\n            display: inline-block;\n            margin: 20px 0;\n            letter-spacing: 8px;\n            box-shadow: 0 8px 30px rgba(52, 152, 219, 0.3);\n        }\n        .instructions {\n            color: #555;\n            font-size: 16px;\n            margin: 20px 0;\n            line-height: 1.6;\n        }\n        .footer {\n            margin-top: 40px;\n            padding-top: 20px;\n            border-top: 1px solid #eee;\n            color: #999;\n            font-size: 14px;\n        }\n        .highlight {\n            color: #3498db;\n            font-weight: bold;\n        }\n    </style>\n</head>\n<body>\n    <div class=\"container\">\n        <div class=\"logo-container\">\n            <img src=\"http://localhost:3000/images/sanrico_logo_1.png\" alt=\"Sanrico Mercantile\" class=\"logo\" onerror=\"this.style.display='none'; this.nextElementSibling.style.display='block';\">\n            <div class=\"company-name\" style=\"display:none;\">Sanrico Mercantile</div>\n        </div>\n        <p class=\"subtitle\">Hardware & Mercantile Store</p>\n        \n        <h1 style=\"color: #2c3e50; margin-bottom: 10px;\">Email Verification Required</h1>\n        \n        <p class=\"greeting\">Hello {{ $json.userName || 'Valued Customer' }},</p>\n        \n        <p class=\"instructions\">\n            Thank you for registering with Sanrico Mercantile! To complete your account setup and start shopping with us, please verify your email address using the verification code below:\n        </p>\n        \n        <div class=\"verification-code\">{{ $json.verificationCode }}</div>\n        \n        <p class=\"instructions\">\n            Enter this <span class=\"highlight\">4-digit code</span> in the verification dialog on our website to activate your account.\n        </p>\n        \n        <p style=\"color: #e74c3c; font-size: 14px; margin-top: 30px;\">\n            This code will expire in <strong>15 minutes</strong> for security purposes.\n        </p>\n        \n        <div class=\"footer\">\n            <p>If you didn't create an account with Sanrico Mercantile, please ignore this email.</p>\n            <p>© 2024 Sanrico Mercantile. All rights reserved.</p>\n        </div>\n    </div>\n</body>\n</html>",
        "options": {
          "allowUnauthorizedCerts": false,
          "ccEmail": "",
          "bccEmail": "",
          "replyTo": "",
          "appendAttribution": false
        }
      },
      "id": "send-email-verification",
      "name": "Send Email Verification",
      "type": "n8n-nodes-base.gmail",
      "typeVersion": 2.1,
      "position": [700, 250],
      "credentials": {
        "gmailOAuth2": {
          "id": "your-gmail-credentials-id",
          "name": "Gmail OAuth2"
        }
      }
    },
    {
      "parameters": {
        "authentication": "oAuth2",
        "sendTo": "={{ $json.to }}",
        "subject": "Password Reset - Sanrico Mercantile",
        "emailType": "html",
        "message": "<!DOCTYPE html>\n<html>\n<head>\n    <meta charset=\"UTF-8\">\n    <title>Password Reset - Sanrico Mercantile</title>\n    <style>\n        body {\n            font-family: 'Segoe UI', Tahoma, Geneva, Verdana, sans-serif;\n            background: linear-gradient(135deg, #667eea 0%, #764ba2 100%);\n            margin: 0;\n            padding: 20px;\n            min-height: 100vh;\n        }\n        .container {\n            max-width: 600px;\n            margin: 0 auto;\n            background: white;\n            border-radius: 20px;\n            padding: 40px;\n            box-shadow: 0 20px 60px rgba(0,0,0,0.1);\n            text-align: center;\n        }\n        .logo-container {\n            margin-bottom: 20px;\n        }\n        .logo {\n            max-width: 200px;\n            height: auto;\n            margin-bottom: 10px;\n        }\n        .company-name {\n            color: #3498db;\n            font-size: 32px;\n            font-weight: bold;\n            margin-bottom: 10px;\n        }\n        .subtitle {\n            color: #666;\n            font-size: 16px;\n            margin-bottom: 30px;\n        }\n        .greeting {\n            font-size: 20px;\n            color: #2c3e50;\n            margin-bottom: 20px;\n        }\n        .reset-button {\n            background: linear-gradient(45deg, #e74c3c, #c0392b);\n            color: white;\n            text-decoration: none;\n            font-size: 18px;\n            font-weight: bold;\n            padding: 15px 30px;\n            border-radius: 10px;\n            display: inline-block;\n            margin: 20px 0;\n            box-shadow: 0 8px 30px rgba(231, 76, 60, 0.3);\n            transition: all 0.3s ease;\n        }\n        .instructions {\n            color: #555;\n            font-size: 16px;\n            margin: 20px 0;\n            line-height: 1.6;\n        }\n        .footer {\n            margin-top: 40px;\n            padding-top: 20px;\n            border-top: 1px solid #eee;\n            color: #999;\n            font-size: 14px;\n        }\n    </style>\n</head>\n<body>\n    <div class=\"container\">\n        <div class=\"logo-container\">\n            <img src=\"http://localhost:3000/images/sanrico_logo_1.png\" alt=\"Sanrico Mercantile\" class=\"logo\" onerror=\"this.style.display='none'; this.nextElementSibling.style.display='block';\">\n            <div class=\"company-name\" style=\"display:none;\">Sanrico Mercantile</div>\n        </div>\n        <p class=\"subtitle\">Hardware & Mercantile Store</p>\n        \n        <h1 style=\"color: #2c3e50; margin-bottom: 10px;\">Password Reset Request</h1>\n        \n        <p class=\"greeting\">Hello {{ $json.userName || 'Valued Customer' }},</p>\n        \n        <p class=\"instructions\">\n            We received a request to reset your password for your Sanrico Mercantile account. Click the button below to create a new password:\n        </p>\n        \n        <a href=\"{{ $json.resetLink }}\" class=\"reset-button\">Reset Password</a>\n        \n        <p class=\"instructions\">\n            If you didn't request a password reset, please ignore this email. Your password will remain unchanged.\n        </p>\n        \n        <p style=\"color: #e74c3c; font-size: 14px; margin-top: 30px;\">\n            This link will expire in <strong>1 hour</strong> for security purposes.\n        </p>\n        \n        <div class=\"footer\">\n            <p>If you're having trouble clicking the button, copy and paste this link into your browser:</p>\n            <p style=\"word-break: break-all; color: #3498db;\">{{ $json.resetLink }}</p>\n            <p>© 2024 Sanrico Mercantile. All rights reserved.</p>\n        </div>\n    </div>\n</body>\n</html>",
        "options": {
          "allowUnauthorizedCerts": false,
          "ccEmail": "",
          "bccEmail": "",
          "replyTo": "",
          "appendAttribution": false
        }
      },
      "id": "send-password-reset",
      "name": "Send Password Reset",
      "type": "n8n-nodes-base.gmail",
      "typeVersion": 2.1,
      "position": [700, 350],
      "credentials": {
        "gmailOAuth2": {
          "id": "your-gmail-credentials-id",
          "name": "Gmail OAuth2"
        }
      }
    },
    {
      "parameters": {
        "respondWith": "json",
        "responseBody": "={{ { \"success\": true, \"message\": \"Email sent successfully\", \"type\": $json.type } }}"
      },
      "id": "response-node",
      "name": "Response",
      "type": "n8n-nodes-base.respondToWebhook",
      "typeVersion": 1.1,
      "position": [900, 300]
    }
  ],
  "connections": {
    "Webhook": {
      "main": [
        [
          {
            "node": "Check Email Type",
            "type": "main",
            "index": 0
          }
        ]
      ]
    },
    "Check Email Type": {
      "main": [
        [
          {
            "node": "Send Email Verification",
            "type": "main",
            "index": 0
          }
        ],
        [
          {
            "node": "Send Password Reset",
            "type": "main",
            "index": 0
          }
        ]
      ]
    },
    "Send Email Verification": {
      "main": [
        [
          {
            "node": "Response",
            "type": "main",
            "index": 0
          }
        ]
      ]
    },
    "Send Password Reset": {
      "main": [
        [
          {
            "node": "Response",
            "type": "main",
            "index": 0
          }
        ]
      ]
    }
  },
  "settings": {
    "executionOrder": "v1"
  },
  "staticData": null,
  "tags": [],
  "triggerCount": 0,
  "updatedAt": "2024-01-01T00:00:00.000Z",
  "versionId": "1"
}
